sharedir/__init__.py
sharedir/sharedir.py
sharedir-1.0.3.dist-info/LICENSE
sharedir-1.0.3.dist-info/METADATA
sharedir-1.0.3.dist-info/WHEEL
sharedir-1.0.3.dist-info/entry_points.txt
sharedir-1.0.3.dist-info/top_level.txt
sharedir-1.0.3.dist-info/RECORD
