Metadata-Version: 2.1
Name: sharedir
Version: 1.0.3
Summary: A simple tool to share files and directories over LAN or internet.
Home-page: https://github.com/spignelon/ShareDir
Author: Ujjawal Saini
Author-email: spignelon@proton.me
License: AGPL-3.0
Project-URL: Homepage, https://github.com/spignelon/ShareDir
Project-URL: Bug Tracker, https://github.com/spignelon/ShareDir/issues
Project-URL: Source Code, https://github.com/spignelon/ShareDir/blob/main/sharedir/sharedir.py
Classifier: Programming Language :: Python :: 3
Classifier: License :: OSI Approved :: GNU Affero General Public License v3
Classifier: Operating System :: OS Independent
Classifier: Development Status :: 5 - Production/Stable
Classifier: Intended Audience :: Developers
Classifier: Intended Audience :: End Users/Desktop
Classifier: Topic :: Utilities
Classifier: Topic :: Communications :: File Sharing
Requires-Python: >=3.6
License-File: LICENSE
Requires-Dist: blinker==1.8.2
Requires-Dist: click==8.1.7
Requires-Dist: diceware==0.10
Requires-Dist: Flask==3.0.3
Requires-Dist: itsdangerous==2.2.0
Requires-Dist: Jinja2==3.1.6
Requires-Dist: MarkupSafe==2.1.5
Requires-Dist: pypng==0.20220715.0
Requires-Dist: qrcode==7.4.2
Requires-Dist: setuptools==75.1.0
Requires-Dist: typing-extensions==4.12.2
Requires-Dist: Werkzeug==3.0.6
